qure/__init__.py
qure/__version__.py
qure/encryption/__init__.py
qure/encryption/encryption.py
qure/generation/__init__.py
qure/generation/generator.py
qure/scanner/__init__.py
qure/scanner/scanner.py
qure/tests/__init__.py
qure/tests/test_encryption.py
qure/tests/test_generator.py
qure/tests/test_scanner.py
qure/tests/test_utils.py
qure/utils/__init__.py
qure/utils/image_utils.py
qure-0.3.dist-info/METADATA
qure-0.3.dist-info/WHEEL
qure-0.3.dist-info/top_level.txt
qure-0.3.dist-info/RECORD
