Metadata-Version: 2.1
Name: qure
Version: 0.3
Summary: A Python package to generate Student Cards with unique Qrcode from CSV or JSON
Home-page: https://github.com/fraterneelyh/qure.git
Author: HOZANA INEZA Fraterne Ely
Author-email: fraterneelyh@gmail.com
Classifier: Programming Language :: Python :: 3
Classifier: License :: OSI Approved :: MIT License
Classifier: Operating System :: OS Independent
Requires-Python: >=3.6
Requires-Dist: qrcode[pil]
Requires-Dist: Pillow
Requires-Dist: pyzbar
Requires-Dist: cryptography
